devolo_home_control_api/__init__.py
devolo_home_control_api/homecontrol.py
devolo_home_control_api/mydevolo.py
devolo_home_control_api/py.typed
devolo_home_control_api/backend/__init__.py
devolo_home_control_api/backend/mprm.py
devolo_home_control_api/backend/mprm_rest.py
devolo_home_control_api/backend/mprm_websocket.py
devolo_home_control_api/devices/__init__.py
devolo_home_control_api/devices/gateway.py
devolo_home_control_api/devices/zwave.py
devolo_home_control_api/exceptions/__init__.py
devolo_home_control_api/exceptions/device.py
devolo_home_control_api/exceptions/gateway.py
devolo_home_control_api/exceptions/general.py
devolo_home_control_api/helper/__init__.py
devolo_home_control_api/helper/names.py
devolo_home_control_api/helper/uid.py
devolo_home_control_api/properties/__init__.py
devolo_home_control_api/properties/binary_sensor_property.py
devolo_home_control_api/properties/binary_switch_property.py
devolo_home_control_api/properties/consumption_property.py
devolo_home_control_api/properties/humidity_bar_property.py
devolo_home_control_api/properties/multi_level_sensor_property.py
devolo_home_control_api/properties/multi_level_switch_property.py
devolo_home_control_api/properties/property.py
devolo_home_control_api/properties/remote_control_property.py
devolo_home_control_api/properties/sensor_property.py
devolo_home_control_api/properties/settings_property.py
devolo_home_control_api/publisher/__init__.py
devolo_home_control_api/publisher/publisher.py
devolo_home_control_api/publisher/updater.py
devolo_home_control_api-0.19.1.dist-info/licenses/LICENSE
devolo_home_control_api-0.19.1.dist-info/METADATA
devolo_home_control_api-0.19.1.dist-info/WHEEL
devolo_home_control_api-0.19.1.dist-info/top_level.txt
devolo_home_control_api-0.19.1.dist-info/RECORD
