Metadata-Version: 2.4
Name: devolo_home_control_api
Version: 0.19.1
Summary: devolo Home Control API in Python
Author-email: Markus Bong <m.bong@famabo.de>, Guido Schmitz <guido.schmitz@fedaix.de>
License-Expression: GPL-3.0-or-later
Project-URL: changelog, https://github.com/2Fake/devolo_home_control_api/docs/CHANGELOG.md
Project-URL: homepage, https://github.com/2Fake/devolo_home_control_api
Classifier: Programming Language :: Python :: 3
Classifier: Operating System :: OS Independent
Requires-Python: >=3.9
License-File: LICENSE
Requires-Dist: python-dateutil>=2.8.0
Requires-Dist: requests>=2.4.0
Requires-Dist: typing-extensions>=4.1.0; python_version < "3.11"
Requires-Dist: websocket_client>=0.58.0
Requires-Dist: zeroconf>=0.38.0
Provides-Extra: dev
Requires-Dist: pre-commit; extra == "dev"
Provides-Extra: test
Requires-Dist: pytest; extra == "test"
Requires-Dist: pytest-cov; extra == "test"
Requires-Dist: pytest-freezer; extra == "test"
Requires-Dist: requests-mock; extra == "test"
Requires-Dist: syrupy; extra == "test"
Dynamic: license-file
